LICENSE
README.md
setup.cfg
setup.py
CryptomusAPI/__init__.py
CryptomusAPI/cryptomusapi.py
CryptomusAPI/exceptions.py
CryptomusAPI.egg-info/PKG-INFO
CryptomusAPI.egg-info/SOURCES.txt
CryptomusAPI.egg-info/dependency_links.txt
CryptomusAPI.egg-info/top_level.txt
CryptomusAPI/api/__init__.py
CryptomusAPI/api/get_asyncio_api.py
CryptomusAPI/enums/__init__.py
CryptomusAPI/enums/base_enum.py
CryptomusAPI/enums/blockchain.py
CryptomusAPI/enums/crypto_currency.py
CryptomusAPI/enums/fiat_currency.py
CryptomusAPI/utils/__init__.py
CryptomusAPI/utils/base.py
CryptomusAPI/utils/models.py