Metadata-Version: 2.1
Name: CryptomusAPI
Version: 1.0.1
Summary: Easy interaction with Cryptomus API, support for asynchronous approaches
Home-page: https://github.com/Fsoky/CryptomusAPI
Author: Fsoky
Author-email: cyberuest0x12@gmail.com
License: MIT
Keywords: api cryptomus asyncio crypto cryptomusapi
Platform: UNKNOWN
Classifier: Programming Language :: Python :: 3
Classifier: License :: OSI Approved :: MIT License
Classifier: Operating System :: OS Independent
License-File: LICENSE
